[
    {
        "creation": "2000",
        "timespan": "P11Y",
        "oci": "06803796940-061301400838",
        "journal_sc": "no",
        "cited": "10.1080/00140138808966724",
        "author_sc": "no",
        "citing": "10.1145/332040.332044"
    },
    {
        "creation": "2000",
        "timespan": "P7Y",
        "oci": "06803796940-061301401159",
        "journal_sc": "no",
        "cited": "10.1080/00140139208967802",
        "author_sc": "no",
        "citing": "10.1145/332040.332044"
    },
    {
        "creation": "2000",
        "timespan": "P11Y",
        "oci": "06803796940-061401389795",
        "journal_sc": "no",
        "cited": "10.1080/00140138808966733",
        "author_sc": "no",
        "citing": "10.1145/332040.332044"
    },
    {
        "creation": "2000",
        "timespan": "P9Y",
        "oci": "06803796940-061403372357",
        "journal_sc": "no",
        "cited": "10.1145/108844.108868",
        "author_sc": "no",
        "citing": "10.1145/332040.332044"
    },
    {
        "creation": "2000",
        "timespan": "P13Y",
        "oci": "06803796940-06140905941",
        "journal_sc": "no",
        "cited": "10.1177/154193128603000403",
        "author_sc": "no",
        "citing": "10.1145/332040.332044"
    },
    {
        "creation": "2000",
        "timespan": "P46Y",
        "oci": "06803796940-061601176573",
        "journal_sc": "no",
        "cited": "10.1037/h0055392",
        "author_sc": "no",
        "citing": "10.1145/332040.332044"
    },
    {
        "creation": "2000",
        "timespan": "P8Y",
        "oci": "06803796940-061703399270",
        "journal_sc": "no",
        "cited": "10.1145/142750.142794",
        "author_sc": "no",
        "citing": "10.1145/332040.332044"
    },
    {
        "creation": "2000",
        "timespan": "P7Y",
        "oci": "06803796940-06402528929",
        "journal_sc": "no",
        "cited": "10.1207/s15327051hci0701_3",
        "author_sc": "no",
        "citing": "10.1145/332040.332044"
    },
    {
        "creation": "2000",
        "timespan": "P1Y",
        "oci": "06803796940-06703788319",
        "journal_sc": "no",
        "cited": "10.1145/302979.302983",
        "author_sc": "no",
        "citing": "10.1145/332040.332044"
    }
]