[
    {
        "creation": "2004",
        "timespan": "P7Y",
        "oci": "062603395817-06101725546",
        "journal_sc": "no",
        "cited": "10.1109/38.511850",
        "author_sc": "no",
        "citing": "10.1145/985692.985711"
    },
    {
        "creation": "2004",
        "timespan": "P4Y",
        "oci": "062603395817-061103360990",
        "journal_sc": "no",
        "cited": "10.1145/344779.344859",
        "author_sc": "no",
        "citing": "10.1145/985692.985711"
    },
    {
        "creation": "2004",
        "timespan": "P12Y",
        "oci": "062603395817-061103361866",
        "journal_sc": "no",
        "cited": "10.1145/133994.134001",
        "author_sc": "no",
        "citing": "10.1145/985692.985711"
    },
    {
        "creation": "2004",
        "timespan": "P2Y",
        "oci": "062603395817-061603525836",
        "journal_sc": "no",
        "cited": "10.1145/502783.502784",
        "author_sc": "no",
        "citing": "10.1145/985692.985711"
    },
    {
        "creation": "2004",
        "timespan": "P8Y",
        "oci": "062603395817-06201714417",
        "journal_sc": "no",
        "cited": "10.1109/38.365005",
        "author_sc": "no",
        "citing": "10.1145/985692.985711"
    },
    {
        "creation": "2004",
        "timespan": "P2Y",
        "oci": "062603395817-06203801194",
        "journal_sc": "no",
        "cited": "10.1145/581710.581718",
        "author_sc": "no",
        "citing": "10.1145/985692.985711"
    },
    {
        "creation": "2004",
        "timespan": "P5Y",
        "oci": "062603395817-06603246915",
        "journal_sc": "no",
        "cited": "10.1007/s003710050148",
        "author_sc": "no",
        "citing": "10.1145/985692.985711"
    }
]