[
    {
        "creation": "2003",
        "timespan": "P22Y",
        "oci": "06603794877-061102705200",
        "journal_sc": "no",
        "cited": "10.1207/s15516709cog0404_2",
        "author_sc": "no",
        "citing": "10.1145/642611.642661"
    },
    {
        "creation": "2003",
        "timespan": "P6Y",
        "oci": "06603794877-061602199966",
        "journal_sc": "no",
        "cited": "10.1006/ijhc.1996.0073",
        "author_sc": "no",
        "citing": "10.1145/642611.642661"
    },
    {
        "creation": "2003",
        "timespan": "P7Y",
        "oci": "06603794877-061602200010",
        "journal_sc": "no",
        "cited": "10.1006/ijhc.1995.1042",
        "author_sc": "no",
        "citing": "10.1145/642611.642661"
    },
    {
        "creation": "2003",
        "timespan": "P2Y",
        "oci": "06603794877-061903105434",
        "journal_sc": "no",
        "cited": "10.1086/209566",
        "author_sc": "no",
        "citing": "10.1145/642611.642661"
    },
    {
        "creation": "2003",
        "timespan": "P3Y",
        "oci": "06603794877-0620150316",
        "journal_sc": "no",
        "cited": "10.1111/0022-4537.00153",
        "author_sc": "no",
        "citing": "10.1145/642611.642661"
    },
    {
        "creation": "2003",
        "timespan": "P3Y",
        "oci": "06603794877-0621077234",
        "journal_sc": "no",
        "cited": "10.1111/j.1559-1816.1999.tb00142.x",
        "author_sc": "no",
        "citing": "10.1145/642611.642661"
    },
    {
        "creation": "2003",
        "timespan": "P47Y",
        "oci": "06603794877-06260489783",
        "journal_sc": "no",
        "cited": "10.1111/j.1467-6494.1955.tb01177.x",
        "author_sc": "no",
        "citing": "10.1145/642611.642661"
    },
    {
        "creation": "2003",
        "timespan": "P5Y",
        "oci": "06603794877-0638038151",
        "journal_sc": "no",
        "cited": "10.1037/0022-3514.72.3.592",
        "author_sc": "no",
        "citing": "10.1145/642611.642661"
    },
    {
        "creation": "2003",
        "timespan": "P3Y",
        "oci": "06603794877-06402529137",
        "journal_sc": "no",
        "cited": "10.1207/s15327051hci1404_2",
        "author_sc": "no",
        "citing": "10.1145/642611.642661"
    }
]