[
    {
        "creation": "2002",
        "timespan": "P3Y",
        "oci": "06403799950-061203385867",
        "journal_sc": "no",
        "cited": "10.1145/302979.302985",
        "author_sc": "no",
        "citing": "10.1145/503376.503428"
    },
    {
        "creation": "2002",
        "timespan": "P12Y",
        "oci": "06403799950-061702144412",
        "journal_sc": "no",
        "cited": "10.1145/67880.1046599",
        "author_sc": "no",
        "citing": "10.1145/503376.503428"
    },
    {
        "creation": "2002",
        "timespan": "P8Y",
        "oci": "06403799950-061703038013",
        "journal_sc": "no",
        "cited": "10.1006/jvlc.1993.1002",
        "author_sc": "no",
        "citing": "10.1145/503376.503428"
    },
    {
        "creation": "2002",
        "timespan": "P1Y",
        "oci": "06403799950-061703538184",
        "journal_sc": "no",
        "cited": "10.1145/355324.355327",
        "author_sc": "no",
        "citing": "10.1145/503376.503428"
    },
    {
        "creation": "2002",
        "timespan": "P3Y",
        "oci": "06403799950-06403799568",
        "journal_sc": "no",
        "cited": "10.1145/632716.632855",
        "author_sc": "no",
        "citing": "10.1145/503376.503428"
    },
    {
        "creation": "2002",
        "timespan": "P4Y",
        "oci": "06403799950-06603597306",
        "journal_sc": "no",
        "cited": "10.1145/274644.274647",
        "author_sc": "no",
        "citing": "10.1145/503376.503428"
    },
    {
        "creation": "2002",
        "timespan": "P5Y",
        "oci": "06403799950-06603899622",
        "journal_sc": "no",
        "cited": "10.1145/232014.232032",
        "author_sc": "no",
        "citing": "10.1145/503376.503428"
    },
    {
        "creation": "2002",
        "timespan": "P2Y",
        "oci": "06403799950-06803693315",
        "journal_sc": "no",
        "cited": "10.1049/ic:20000511",
        "author_sc": "no",
        "citing": "10.1145/503376.503428"
    },
    {
        "creation": "2002",
        "timespan": "P2Y",
        "oci": "06403799950-06903411748",
        "journal_sc": "no",
        "cited": "10.1145/332040.332460",
        "author_sc": "no",
        "citing": "10.1145/503376.503428"
    }
]