[
    {
        "creation": "2003",
        "timespan": "P8Y",
        "oci": "06603795036-061503393122",
        "journal_sc": "no",
        "cited": "10.1145/223355.223665",
        "author_sc": "no",
        "citing": "10.1145/642611.642657"
    },
    {
        "creation": "2003",
        "timespan": "P1Y",
        "oci": "06603795036-061801191664",
        "journal_sc": "no",
        "cited": "10.1177/089443930101900204",
        "author_sc": "no",
        "citing": "10.1145/642611.642657"
    },
    {
        "creation": "2003",
        "timespan": "P7Y",
        "oci": "06603795036-06210686749",
        "journal_sc": "no",
        "cited": "10.1518/001872095779049462",
        "author_sc": "no",
        "citing": "10.1145/642611.642657"
    },
    {
        "creation": "2003",
        "timespan": "P8Y",
        "oci": "06603795036-062501135260",
        "journal_sc": "no",
        "cited": "10.1177/154193129403801806",
        "author_sc": "no",
        "citing": "10.1145/642611.642657"
    },
    {
        "creation": "2003",
        "timespan": "P1Y",
        "oci": "06603795036-06402529166",
        "journal_sc": "no",
        "cited": "10.1207/s15327051hci16234_05",
        "author_sc": "no",
        "citing": "10.1145/642611.642657"
    },
    {
        "creation": "2003",
        "timespan": "P5Y",
        "oci": "06603795036-06503007752",
        "journal_sc": "no",
        "cited": "10.1006/jcss.1997.1504",
        "author_sc": "no",
        "citing": "10.1145/642611.642657"
    },
    {
        "creation": "2003",
        "timespan": "P1Y",
        "oci": "06603795036-06503809991",
        "journal_sc": "no",
        "cited": "10.1145/503376.503394",
        "author_sc": "no",
        "citing": "10.1145/642611.642657"
    },
    {
        "creation": "2003",
        "timespan": "P5Y",
        "oci": "06603795036-06603298988",
        "journal_sc": "no",
        "cited": "10.1023/a:1009715923555",
        "author_sc": "no",
        "citing": "10.1145/642611.642657"
    },
    {
        "creation": "2003",
        "timespan": "P1Y",
        "oci": "06603795036-06901993546",
        "journal_sc": "no",
        "cited": "10.1287/mnsc.47.5.647.10481",
        "author_sc": "no",
        "citing": "10.1145/642611.642657"
    }
]