[
    {
        "creation": "2003",
        "timespan": "P16Y",
        "oci": "06503809680-061103361564",
        "journal_sc": "no",
        "cited": "10.1145/37401.37407",
        "author_sc": "no",
        "citing": "10.1145/642611.642677"
    },
    {
        "creation": "2003",
        "timespan": "P7Y",
        "oci": "06503809680-061103398886",
        "journal_sc": "no",
        "cited": "10.1145/238386.238566",
        "author_sc": "no",
        "citing": "10.1145/642611.642677"
    },
    {
        "creation": "2003",
        "timespan": "P10Y",
        "oci": "06503809680-061103399627",
        "journal_sc": "no",
        "cited": "10.1145/168642.168648",
        "author_sc": "no",
        "citing": "10.1145/642611.642677"
    },
    {
        "creation": "2003",
        "timespan": "P4Y",
        "oci": "06503809680-061103399694",
        "journal_sc": "no",
        "cited": "10.1145/320719.322594",
        "author_sc": "no",
        "citing": "10.1145/642611.642677"
    },
    {
        "creation": "2003",
        "timespan": "P11Y",
        "oci": "06503809680-061203379734",
        "journal_sc": "no",
        "cited": "10.1145/143457.143473",
        "author_sc": "no",
        "citing": "10.1145/642611.642677"
    },
    {
        "creation": "2003",
        "timespan": "P10Y",
        "oci": "06503809680-061203385793",
        "journal_sc": "no",
        "cited": "10.1145/168642.168647",
        "author_sc": "no",
        "citing": "10.1145/642611.642677"
    },
    {
        "creation": "2003",
        "timespan": "P6Y",
        "oci": "06503809680-061303331625",
        "journal_sc": "no",
        "cited": "10.1145/1120212.1120387",
        "author_sc": "no",
        "citing": "10.1145/642611.642677"
    },
    {
        "creation": "2003",
        "timespan": "P6Y",
        "oci": "06503809680-061403372768",
        "journal_sc": "no",
        "cited": "10.1145/263407.263541",
        "author_sc": "no",
        "citing": "10.1145/642611.642677"
    },
    {
        "creation": "2003",
        "timespan": "P7Y",
        "oci": "06503809680-061503392809",
        "journal_sc": "no",
        "cited": "10.1145/237091.237109",
        "author_sc": "no",
        "citing": "10.1145/642611.642677"
    },
    {
        "creation": "2003",
        "timespan": "P8Y",
        "oci": "06503809680-061503393004",
        "journal_sc": "no",
        "cited": "10.1145/215585.215976",
        "author_sc": "no",
        "citing": "10.1145/642611.642677"
    },
    {
        "creation": "2003",
        "timespan": "P5Y",
        "oci": "06503809680-061503393030",
        "journal_sc": "no",
        "cited": "10.1145/288392.288585",
        "author_sc": "no",
        "citing": "10.1145/642611.642677"
    },
    {
        "creation": "2003",
        "timespan": "P15Y",
        "oci": "06503809680-061603520845",
        "journal_sc": "no",
        "cited": "10.1145/45075.46162",
        "author_sc": "no",
        "citing": "10.1145/642611.642677"
    },
    {
        "creation": "2003",
        "timespan": "P20Y",
        "oci": "06503809680-061701129690",
        "journal_sc": "no",
        "cited": "10.1075/idj.3.3.05bor",
        "author_sc": "no",
        "citing": "10.1145/642611.642677"
    },
    {
        "creation": "2003",
        "timespan": "P6Y",
        "oci": "06503809680-062602180505",
        "journal_sc": "no",
        "cited": "10.7551/mitpress/5677.001.0001",
        "author_sc": "no",
        "citing": "10.1145/642611.642677"
    },
    {
        "creation": "2003",
        "timespan": "P1Y",
        "oci": "06503809680-06403799301",
        "journal_sc": "no",
        "cited": "10.1145/571985.572014",
        "author_sc": "no",
        "citing": "10.1145/642611.642677"
    },
    {
        "creation": "2003",
        "timespan": "P1Y",
        "oci": "06503809680-06603794822",
        "journal_sc": "no",
        "cited": "10.1145/571985.571997",
        "author_sc": "no",
        "citing": "10.1145/642611.642677"
    }
]