[
    {
        "creation": "2004",
        "timespan": "P4Y",
        "oci": "062303370767-061103393172",
        "journal_sc": "no",
        "cited": "10.1145/358916.359003",
        "author_sc": "no",
        "citing": "10.1145/985692.985717"
    },
    {
        "creation": "2004",
        "timespan": "P8Y",
        "oci": "062303370767-061103393183",
        "journal_sc": "no",
        "cited": "10.1145/240080.240316",
        "author_sc": "no",
        "citing": "10.1145/985692.985717"
    },
    {
        "creation": "2004",
        "timespan": "P4Y",
        "oci": "062303370767-061203379706",
        "journal_sc": "no",
        "cited": "10.1145/358916.358975",
        "author_sc": "no",
        "citing": "10.1145/985692.985717"
    },
    {
        "creation": "2004",
        "timespan": "P9Y",
        "oci": "062303370767-061603520273",
        "journal_sc": "no",
        "cited": "10.1145/174666.174668",
        "author_sc": "no",
        "citing": "10.1145/985692.985717"
    },
    {
        "creation": "2004",
        "timespan": "P3Y",
        "oci": "062303370767-0620338817",
        "journal_sc": "no",
        "cited": "10.1023/a:1008748724225",
        "author_sc": "no",
        "citing": "10.1145/985692.985717"
    },
    {
        "creation": "2004",
        "timespan": "P4Y",
        "oci": "062303370767-06203799759",
        "journal_sc": "no",
        "cited": "10.1145/633292.633351",
        "author_sc": "no",
        "citing": "10.1145/985692.985717"
    },
    {
        "creation": "2004",
        "timespan": "P16Y",
        "oci": "062303370767-062201197163",
        "journal_sc": "no",
        "cited": "10.1177/009365087014005007",
        "author_sc": "no",
        "citing": "10.1145/985692.985717"
    },
    {
        "creation": "2004",
        "timespan": "P2Y",
        "oci": "062303370767-062301030901",
        "journal_sc": "no",
        "cited": "10.1287/orsc.12.3.346.10098",
        "author_sc": "no",
        "citing": "10.1145/985692.985717"
    },
    {
        "creation": "2004",
        "timespan": "P5Y",
        "oci": "062303370767-062301766821",
        "journal_sc": "no",
        "cited": "10.1145/307736.307754",
        "author_sc": "no",
        "citing": "10.1145/985692.985717"
    },
    {
        "creation": "2004",
        "timespan": "P3Y",
        "oci": "062303370767-062301766929",
        "journal_sc": "no",
        "cited": "10.1145/605647.605651",
        "author_sc": "no",
        "citing": "10.1145/985692.985717"
    },
    {
        "creation": "2004",
        "timespan": "P2Y",
        "oci": "062303370767-062603402251",
        "journal_sc": "no",
        "cited": "10.1145/587078.587110",
        "author_sc": "no",
        "citing": "10.1145/985692.985717"
    },
    {
        "creation": "2004",
        "timespan": "P2Y",
        "oci": "062303370767-06303801656",
        "journal_sc": "no",
        "cited": "10.1145/587078.587080",
        "author_sc": "no",
        "citing": "10.1145/985692.985717"
    },
    {
        "creation": "2004",
        "timespan": "P2Y",
        "oci": "062303370767-06402051870",
        "journal_sc": "no",
        "cited": "10.1145/587078.587081",
        "author_sc": "no",
        "citing": "10.1145/985692.985717"
    },
    {
        "creation": "2004",
        "timespan": "P16Y",
        "oci": "062303370767-06402528980",
        "journal_sc": "no",
        "cited": "10.1207/s15327051hci0301_3",
        "author_sc": "no",
        "citing": "10.1145/985692.985717"
    },
    {
        "creation": "2004",
        "timespan": "P3Y",
        "oci": "062303370767-06402529167",
        "journal_sc": "no",
        "cited": "10.1207/s15327051hci1523_4",
        "author_sc": "no",
        "citing": "10.1145/985692.985717"
    },
    {
        "creation": "2004",
        "timespan": "P1Y",
        "oci": "062303370767-06503810154",
        "journal_sc": "no",
        "cited": "10.1145/642611.642672",
        "author_sc": "no",
        "citing": "10.1145/985692.985717"
    },
    {
        "creation": "2004",
        "timespan": "P2Y",
        "oci": "062303370767-06603794907",
        "journal_sc": "no",
        "cited": "10.1145/503376.503408",
        "author_sc": "no",
        "citing": "10.1145/985692.985717"
    },
    {
        "creation": "2004",
        "timespan": "P5Y",
        "oci": "062303370767-06603796406",
        "journal_sc": "no",
        "cited": "10.1145/320297.320333",
        "author_sc": "no",
        "citing": "10.1145/985692.985717"
    }
]