[
    {
        "creation": "2000",
        "timespan": "P2Y",
        "oci": "061203385941-061203379937",
        "journal_sc": "no",
        "cited": "10.1145/289444.289500",
        "author_sc": "no",
        "citing": "10.1145/332040.332409"
    },
    {
        "creation": "2000",
        "timespan": "P1Y",
        "oci": "061203385941-061603535726",
        "journal_sc": "no",
        "cited": "10.1145/274430.274435",
        "author_sc": "no",
        "citing": "10.1145/332040.332409"
    },
    {
        "creation": "2000",
        "timespan": "P4Y",
        "oci": "061203385941-061703399250",
        "journal_sc": "no",
        "cited": "10.1145/238386.238530",
        "author_sc": "no",
        "citing": "10.1145/332040.332409"
    },
    {
        "creation": "2000",
        "timespan": "P2Y",
        "oci": "061203385941-06503612451",
        "journal_sc": "no",
        "cited": "10.1145/274644.274694",
        "author_sc": "no",
        "citing": "10.1145/332040.332409"
    }
]