[
    {
        "creation": "2001",
        "timespan": "P0Y",
        "oci": "061703391392-061203479425",
        "journal_sc": "no",
        "cited": "10.1145/355112.355120",
        "author_sc": "no",
        "citing": "10.1145/365024.365034"
    },
    {
        "creation": "2001",
        "timespan": "P4Y",
        "oci": "061703391392-06701028287",
        "journal_sc": "no",
        "cited": "10.1007/bf02639315",
        "author_sc": "no",
        "citing": "10.1145/365024.365034"
    }
]